xplorts/__init__.py
xplorts/base.py
xplorts/dutils.py
xplorts/ghostbokeh.py
xplorts/growthcomps.py
xplorts/slideselect.py
xplorts/stacks_util.py
xplorts/dashboard/__init__.py
xplorts/dashboard/__main__.py
xplorts/dashboard/xpdashboard.py
xplorts/dblprod/__init__.py
xplorts/dblprod/__main__.py
xplorts/dblprod/xpdblprod.py
xplorts/diff/__init__.py
xplorts/diff/__main__.py
xplorts/diff/diff.py
xplorts/diff/xpdiff.py
xplorts/heatmap/__init__.py
xplorts/heatmap/__main__.py
xplorts/heatmap/heatmap.py
xplorts/heatmap/xpheatmap.py
xplorts/lines/__init__.py
xplorts/lines/__main__.py
xplorts/lines/lines.py
xplorts/lines/xplines.py
xplorts/scatter/__init__.py
xplorts/scatter/__main__.py
xplorts/scatter/scatter.py
xplorts/scatter/xpscatter.py
xplorts/snapcomp/__init__.py
xplorts/snapcomp/__main__.py
xplorts/snapcomp/snapcomp.py
xplorts/snapcomp/xpsnapcomp.py
xplorts/stacks/__init__.py
xplorts/stacks/__main__.py
xplorts/stacks/bokeh_stacks.py
xplorts/stacks/stacks.py
xplorts/stacks/stacks_util.py
xplorts/stacks/xpstacks.py
xplorts/tscomp/__init__.py
xplorts/tscomp/__main__.py
xplorts/tscomp/tscomp.py
xplorts/tscomp/xptscomp.py
xplorts/utils/__init__.py
xplorts/utils/ukons_lcli_to_csv.py
xplorts/utils/ukons_lprod_to_csv.py
xplorts/utils/ukons_psp_to_csv.py
xplorts-1.2.dist-info/METADATA
xplorts-1.2.dist-info/WHEEL
xplorts-1.2.dist-info/entry_points.txt
xplorts-1.2.dist-info/licenses/LICENSE
xplorts-1.2.dist-info/RECORD
