Metadata-Version: 2.1
Name: xplorts
Version: 1.2
Summary: Make standalone interactive HTML charts to explore time series datasets
Project-URL: Homepage, https://github.com/xplorts/xplorts
Project-URL: Bug Tracker, https://github.com/xplorts/xplorts/issues
Author-email: Todd M Bailey <tmb@baileywick.plus.com>
License: Copyright 2023 Todd Bailey
License-File: LICENSE
Classifier: Development Status :: 3 - Alpha
Classifier: License :: OSI Approved :: BSD License
Classifier: Operating System :: OS Independent
Classifier: Programming Language :: Python :: 3
Requires-Python: >=3.6
Requires-Dist: bokeh>=2.3.2
Requires-Dist: numpy>=1.19.2
Requires-Dist: pandas>=1.1.5
Requires-Dist: pyyaml>=5.4.1
Requires-Dist: xlrd>=2.0.1
